watching_testrunner.py
watching_testrunner-1.2.1.dist-info/METADATA
watching_testrunner-1.2.1.dist-info/WHEEL
watching_testrunner-1.2.1.dist-info/entry_points.txt
watching_testrunner-1.2.1.dist-info/top_level.txt
watching_testrunner-1.2.1.dist-info/zip-safe
watching_testrunner-1.2.1.dist-info/RECORD
