Metadata-Version: 2.1
Name: watching-testrunner
Version: 1.2.1
Summary: Automatic test execution on file changes
Home-page: https://github.com/tony/watching-testrunner
Author: Felix Schwarz, Martin Häcker, Robert Buchholz
Author-email: felix.schwarz@web.de, spamfaenger@gmx.de, rbu@rbu.sh, tony@git-pull.com
License: UNKNOWN
Project-URL: Documentation, https://github.com/tony/watching-testrunner
Project-URL: Changes, https://github.com/tony/watching-testrunner/blob/master/CHANGES
Project-URL: Code, https://github.com/tony/watching-testrunner
Project-URL: Issue tracker, https://github.com/tony/watching-testrunner/issues
Project-URL: Q & A, https://github.com/tony/watching-testrunner/discussions
Keywords: unit testing automation automatic test runner
Platform: UNKNOWN
Classifier: License :: OSI Approved :: BSD License
Classifier: Programming Language :: Python
Classifier: Programming Language :: Python :: 2.7
Classifier: Programming Language :: Python :: 3.3
Classifier: Programming Language :: Python :: 3.4
Classifier: Programming Language :: Python :: 3.5
Classifier: Programming Language :: Python :: 3.6
Classifier: Programming Language :: Python :: 3.7
Classifier: Programming Language :: Python :: 3.8
Classifier: Programming Language :: Python :: 3.9
Classifier: Programming Language :: Python :: 3.10
Classifier: Environment :: Console
Classifier: Intended Audience :: Developers
Classifier: Topic :: System :: Shells
Classifier: Topic :: Software Development :: Testing
Classifier: Topic :: Utilities
